README.rst
setup.py
torinja.py
torinja.egg-info/PKG-INFO
torinja.egg-info/SOURCES.txt
torinja.egg-info/dependency_links.txt
torinja.egg-info/top_level.txt