Metadata-Version: 1.1
Name: torinja
Version: 0.1.0
Summary: Integrate Tornado Web Framework and Jinja2 Templates
Home-page: https://github.com/afg984/torinja
Author: afg984
Author-email: afg984@gmail.com
License: BSD
Platform: any
Classifier: Development Status :: 3 - Alpha
Classifier: Environment :: Web Environment
Classifier: Intended Audience :: Developers
Classifier: License :: OSI Approved :: BSD License
Classifier: Programming Language :: Python :: 2.7
Classifier: Programming Language :: Python :: 3
Classifier: Topic :: Internet :: WWW/HTTP
